<ui>
    <popup name="TrayIconMenu" action="TrayIconMenuAction">
    	<placeholder name="TrayIconMenuPlaceholder0" />
    	<placeholder name="TrayNewNotePlaceholder">
        	<menuitem name="TrayNewNote" action="TrayNewNoteAction" />
        </placeholder>
        <menuitem name="ShowSearchAllNotes" action="ShowSearchAllNotesAction" />
        <placeholder name="TrayIconMenuPlaceholder1" />
    </popup>
<!-- The following are not implemented yet
    <toolbar name="NoteWindowToolbar" action="NoteWindowToolbarAction">
    	<placeholder name="NoteWindowToolbarStartPlaceholder" />
    	<toolitem name="SearchToolItem" action="SearchToolItemAction" />
    	<toolitem name="LinkToolItem" action="LinkToolItemAction" />
    	<toolitem name="TextToolItem" action="TextToolItemAction">
    		<menu name="TextToolItemMenu" action="TextToolItemMenuAction">
	    		<placeholder name="TextToolMenuPlaceholder" />
	    	</menu>
    	</toolitem>
    	<toolitem name="ToolsToolItem" action="ToolsToolItemAction">
    		<menu name="ToolsToolItemMenu" action="ToolsToolItemMenuAction">
    			<placeholder name="ToolsToolMenuPlaceholder" />
    		</menu>
    	</toolitem>
    	<separator />
    	<toolitem name="DeleteToolItem" action="DeleteToolItemAction" />
    	<placeholder name="NoteWindowToolbarEndPlaceholder" />
    </toolbar>
    <popup name="TrayIconRightClickMenu" action="TrayIconRightClickMenuAction">
        <menuitem name="OpenPluginsFolder" action="OpenPluginsFolderAction" />
        <separator />
        <menuitem name="ShowPreferences" action="ShowPreferencesAction" />
        <menuitem name="ShowHelp" action="ShowHelpAction" />
        <menuitem name="ShowAbout" action="ShowAboutAction" />
        <separator />
        <menuitem name="QuitGNote" action="QuitGNoteAction" />
    </popup>
-->
</ui>
